cophi/__init__.py
cophi/__version__.py
cophi/api.py
cophi/dkpro/__init__.py
cophi/dkpro/api.py
cophi/dkpro/core.py
cophi/dkpro/model.py
cophi/dkpro/utils.py
cophi/text/__init__.py
cophi/text/complexity.py
cophi/text/model.py
cophi/text/utils.py
cophi-1.3.2.dist-info/METADATA
cophi-1.3.2.dist-info/WHEEL
cophi-1.3.2.dist-info/top_level.txt
cophi-1.3.2.dist-info/RECORD
