Metadata-Version: 2.1
Name: cophi
Version: 1.3.2
Summary: A library for preprocessing.
Home-page: https://github.com/cophi-wue/cophi-toolbox
Author: Chair of Computer Philology and Modern German Literary History
License: Apache 2.0
Platform: UNKNOWN
Classifier: Programming Language :: Python
Classifier: Programming Language :: Python :: 3
Classifier: Programming Language :: Python :: 3.4
Classifier: Programming Language :: Python :: 3.5
Classifier: Programming Language :: Python :: 3.6
Classifier: Programming Language :: Python :: 3.7
Classifier: Programming Language :: Python :: Implementation :: CPython
Requires-Python: >=3.4.0
Requires-Dist: pandas (>=0.23.4)
Requires-Dist: numpy (>=1.15.0)
Requires-Dist: lxml (>=4.2.4)
Requires-Dist: regex (>=2018.07.11)
